.coveragerc
.environment.yml
.gitignore
.readthedocs.yml
.travis.yml
AUTHORS.rst
CHANGES.rst
LICENSE
README.rst
local_run_config_file.ini
local_run_config_file_cluster.ini
requirements.txt
setup.cfg
setup.py
test-requirements.txt
test.txt
docs/Makefile
docs/authors.rst
docs/changes.rst
docs/conf.py
docs/documentation.md
docs/index.rst
docs/license.rst
docs/notes_on_tools.txt
docs/_static/.gitignore
docs/documentation_images/Fig_01_model_overview.jpg
docs/documentation_images/Fig_02_model_flow.jpg
docs/documentation_images/Fig_03_ULM_main_classes.jpg
docs/documentation_images/Fig_XX_constrained_optimised_modes.jpg
docs/documentation_images/Fig_XX_dwelling_stock.jpg
docs/documentation_images/Fig_XX_peak_shifting.jpg
docs/documentation_images/Fig_XX_supply_demand_linkage.jpg
docs/documentation_images/docs-latest-brightgreen.svg
energy_demand/__init__.py
energy_demand/enduse_func.py
energy_demand/main.py
energy_demand/model.py
energy_demand/wrapper_model.py
energy_demand.egg-info/PKG-INFO
energy_demand.egg-info/SOURCES.txt
energy_demand.egg-info/dependency_links.txt
energy_demand.egg-info/entry_points.txt
energy_demand.egg-info/requires.txt
energy_demand.egg-info/top_level.txt
energy_demand.egg-info/zip-safe
energy_demand/assumptions/__init__.py
energy_demand/assumptions/fuel_shares.py
energy_demand/assumptions/general_assumptions.py
energy_demand/assumptions/strategy_vars_def.py
energy_demand/basic/__init__.py
energy_demand/basic/basic_functions.py
energy_demand/basic/conversions.py
energy_demand/basic/date_prop.py
energy_demand/basic/demand_supply_interaction.py
energy_demand/basic/logger_setup.py
energy_demand/basic/lookup_tables.py
energy_demand/basic/testing_functions.py
energy_demand/cli/__init__.py
energy_demand/dwelling_stock/__init__.py
energy_demand/dwelling_stock/dw_stock.py
energy_demand/geography/__init__.py
energy_demand/geography/region.py
energy_demand/geography/spatial_diffusion.py
energy_demand/geography/weather_region.py
energy_demand/geography/weather_station_location.py
energy_demand/geography/write_shp.py
energy_demand/initalisations/__init__.py
energy_demand/initalisations/helpers.py
energy_demand/plotting/__init__.py
energy_demand/plotting/_test.py
energy_demand/plotting/basic_plot_functions.py
