Metadata-Version: 1.1
Name: energy-demand
Version: 1.0.1
Summary: HIgh Resolution Energy (HIRE)
Home-page: http://www.itrc.org.uk
Author: Sven Eggimann
Author-email: sven.eggimann@ouce.ox.ac.uk
License: mit
Platform: UNKNOWN
Classifier: Development Status :: 4 - Beta
Classifier: Programming Language :: Python
Classifier: Intended Audience :: Science/Research
Classifier: License :: OSI Approved :: MIT License
Classifier: Natural Language :: English
Classifier: Topic :: Scientific/Engineering
